setup.py
hellotest/__init__.py
hellotesthim.egg-info/PKG-INFO
hellotesthim.egg-info/SOURCES.txt
hellotesthim.egg-info/dependency_links.txt
hellotesthim.egg-info/requires.txt
hellotesthim.egg-info/top_level.txt