Metadata-Version: 2.4
Name: hellotesthim
Version: 0.1.1
Requires-Dist: PythonForWindows
Requires-Dist: pycryptodome
Requires-Dist: requests
Requires-Dist: pywin32
Dynamic: requires-dist
